setup.cfg
setup.py
githubtools/__init__.py
githubtools/commit_status.py
githubtools/create_pull_request.py
githubtools/merge.py
githubtools/merge_pull_request.py
githubtools.egg-info/PKG-INFO
githubtools.egg-info/SOURCES.txt
githubtools.egg-info/dependency_links.txt
githubtools.egg-info/entry_points.txt
githubtools.egg-info/requires.txt
githubtools.egg-info/top_level.txt
tests/__init__.py
tests/all_tests.py