Metadata-Version: 1.0
Name: githubtools
Version: 0.3.0
Summary: Some simple commandline tools for interacting with github: status, merge, pull, etc.
Home-page: UNKNOWN
Author: nricklin
Author-email: nricklin@digitalglobe.com
License: MIT
Platform: Posix; MacOS X; Windows
